setup.py
a3rt/a3rt.py
a3rt_sdk_py.egg-info/PKG-INFO
a3rt_sdk_py.egg-info/SOURCES.txt
a3rt_sdk_py.egg-info/dependency_links.txt
a3rt_sdk_py.egg-info/requires.txt
a3rt_sdk_py.egg-info/top_level.txt